chinaapi
