Metadata-Version: 1.1
Name: chinaapi
Version: 0.8.6
Summary: Python SDK For China API: Sina Weibo, QQ Weibo, Taobao, Renren, Douban
Home-page: https://github.com/smallcode/ChinaAPI
Author: smallcode
Author-email: 45945756@qq.com
License: Apache 2.0
Platform: UNKNOWN
Classifier: Development Status :: 5 - Production/Stable
Classifier: Intended Audience :: Developers
Classifier: License :: OSI Approved :: Apache Software License
Classifier: Programming Language :: Python
Classifier: Topic :: Internet :: WWW/HTTP :: Dynamic Content
Classifier: Topic :: Software Development :: Libraries :: Python Modules
